[{"date":"2026-03-28","rail_lrt_ampang":53057,"rail_lrt_kj":118090,"rail_mrt_kajang":146263,"rail_mrt_pjy":32628,"rail_monorail":41364,"bus_rkl":13101},{"date":"2026-03-29","rail_lrt_ampang":50349,"rail_lrt_kj":109870,"rail_mrt_kajang":126635,"rail_mrt_pjy":29267,"rail_monorail":36887,"bus_rkl":11068},{"date":"2026-03-30","rail_lrt_ampang":81092,"rail_lrt_kj":227007,"rail_mrt_kajang":217278,"rail_mrt_pjy":53702,"rail_monorail":48594,"bus_rkl":23574},{"date":"2026-03-31","rail_lrt_ampang":83385,"rail_lrt_kj":244602,"rail_mrt_kajang":235014,"rail_mrt_pjy":55178,"rail_monorail":50279,"bus_rkl":25034},{"date":"2026-04-01","rail_lrt_ampang":85353,"rail_lrt_kj":247809,"rail_mrt_kajang":236201,"rail_mrt_pjy":56078,"rail_monorail":51234,"bus_rkl":25863},{"date":"2026-04-02","rail_lrt_ampang":84851,"rail_lrt_kj":246862,"rail_mrt_kajang":231927,"rail_mrt_pjy":56402,"rail_monorail":51302,"bus_rkl":25048},{"date":"2026-04-03","rail_lrt_ampang":86949,"rail_lrt_kj":239579,"rail_mrt_kajang":238658,"rail_mrt_pjy":56247,"rail_monorail":58101,"bus_rkl":24351},{"date":"2026-04-04","rail_lrt_ampang":62639,"rail_lrt_kj":139575,"rail_mrt_kajang":168861,"rail_mrt_pjy":39370,"rail_monorail":49522,"bus_rkl":15308},{"date":"2026-04-05","rail_lrt_ampang":58674,"rail_lrt_kj":126318,"rail_mrt_kajang":142106,"rail_mrt_pjy":32268,"rail_monorail":43617,"bus_rkl":12339},{"date":"2026-04-06","rail_lrt_ampang":83594,"rail_lrt_kj":234749,"rail_mrt_kajang":221168,"rail_mrt_pjy":54458,"rail_monorail":51071,"bus_rkl":21267},{"date":"2026-04-07","rail_lrt_ampang":85901,"rail_lrt_kj":250376,"rail_mrt_kajang":235814,"rail_mrt_pjy":56838,"rail_monorail":52983,"bus_rkl":22329},{"date":"2026-04-08","rail_lrt_ampang":86787,"rail_lrt_kj":254684,"rail_mrt_kajang":239387,"rail_mrt_pjy":57188,"rail_monorail":53750,"bus_rkl":21947},{"date":"2026-04-09","rail_lrt_ampang":86815,"rail_lrt_kj":249637,"rail_mrt_kajang":235433,"rail_mrt_pjy":56785,"rail_monorail":53383,"bus_rkl":21962},{"date":"2026-04-10","rail_lrt_ampang":86554,"rail_lrt_kj":240753,"rail_mrt_kajang":238243,"rail_mrt_pjy":57253,"rail_monorail":55794,"bus_rkl":22156},{"date":"2026-04-11","rail_lrt_ampang":62025,"rail_lrt_kj":143708,"rail_mrt_kajang":176057,"rail_mrt_pjy":36378,"rail_monorail":49401,"bus_rkl":16276},{"date":"2026-04-12","rail_lrt_ampang":57917,"rail_lrt_kj":127711,"rail_mrt_kajang":147534,"rail_mrt_pjy":33219,"rail_monorail":42869,"bus_rkl":13258},{"date":"2026-04-13","rail_lrt_ampang":83235,"rail_lrt_kj":232722,"rail_mrt_kajang":224922,"rail_mrt_pjy":55439,"rail_monorail":50390,"bus_rkl":24531},{"date":"2026-04-14","rail_lrt_ampang":83630,"rail_lrt_kj":244720,"rail_mrt_kajang":232609,"rail_mrt_pjy":55368,"rail_monorail":52097,"bus_rkl":25437},{"date":"2026-04-15","rail_lrt_ampang":85882,"rail_lrt_kj":249014,"rail_mrt_kajang":239051,"rail_mrt_pjy":56671,"rail_monorail":52334,"bus_rkl":26963},{"date":"2026-04-16","rail_lrt_ampang":85231,"rail_lrt_kj":244494,"rail_mrt_kajang":234459,"rail_mrt_pjy":56199,"rail_monorail":52332,"bus_rkl":25796},{"date":"2026-04-17","rail_lrt_ampang":87844,"rail_lrt_kj":240745,"rail_mrt_kajang":239135,"rail_mrt_pjy":63253,"rail_monorail":55433,"bus_rkl":25859},{"date":"2026-04-18","rail_lrt_ampang":60816,"rail_lrt_kj":138172,"rail_mrt_kajang":174625,"rail_mrt_pjy":50757,"rail_monorail":50219,"bus_rkl":20394},{"date":"2026-04-19","rail_lrt_ampang":57243,"rail_lrt_kj":122474,"rail_mrt_kajang":142900,"rail_mrt_pjy":31828,"rail_monorail":40853,"bus_rkl":15926},{"date":"2026-04-20","rail_lrt_ampang":83663,"rail_lrt_kj":234361,"rail_mrt_kajang":222305,"rail_mrt_pjy":55114,"rail_monorail":50580,"bus_rkl":25284},{"date":"2026-04-21","rail_lrt_ampang":82916,"rail_lrt_kj":241111,"rail_mrt_kajang":228996,"rail_mrt_pjy":55256,"rail_monorail":51028,"bus_rkl":26307},{"date":"2026-04-22","rail_lrt_ampang":84248,"rail_lrt_kj":245927,"rail_mrt_kajang":234552,"rail_mrt_pjy":55388,"rail_monorail":51352,"bus_rkl":26646},{"date":"2026-04-23","rail_lrt_ampang":82499,"rail_lrt_kj":240054,"rail_mrt_kajang":229832,"rail_mrt_pjy":55118,"rail_monorail":50562,"bus_rkl":25856},{"date":"2026-04-24","rail_lrt_ampang":86577,"rail_lrt_kj":237344,"rail_mrt_kajang":232845,"rail_mrt_pjy":55310,"rail_monorail":56738,"bus_rkl":24681},{"date":"2026-04-25","rail_lrt_ampang":63512,"rail_lrt_kj":140939,"rail_mrt_kajang":171142,"rail_mrt_pjy":37267,"rail_monorail":51176,"bus_rkl":15505},{"date":"2026-04-26","rail_lrt_ampang":60105,"rail_lrt_kj":127860,"rail_mrt_kajang":144596,"rail_mrt_pjy":34333,"rail_monorail":45365,"bus_rkl":13250},{"date":"2026-04-27","rail_lrt_ampang":81286,"rail_lrt_kj":226875,"rail_mrt_kajang":219447,"rail_mrt_pjy":54150,"rail_monorail":49652,"bus_rkl":24976},{"date":"2026-04-28","rail_lrt_ampang":82315,"rail_lrt_kj":237474,"rail_mrt_kajang":229744,"rail_mrt_pjy":54455,"rail_monorail":50622,"bus_rkl":25711},{"date":"2026-04-29","rail_lrt_ampang":84279,"rail_lrt_kj":241316,"rail_mrt_kajang":234632,"rail_mrt_pjy":61185,"rail_monorail":53815,"bus_rkl":27311},{"date":"2026-04-30","rail_lrt_ampang":85967,"rail_lrt_kj":243464,"rail_mrt_kajang":251551,"rail_mrt_pjy":59775,"rail_monorail":61107,"bus_rkl":27902},{"date":"2026-05-01","rail_lrt_ampang":66899,"rail_lrt_kj":146774,"rail_mrt_kajang":200861,"rail_mrt_pjy":39546,"rail_monorail":66550,"bus_rkl":15135},{"date":"2026-05-02","rail_lrt_ampang":66013,"rail_lrt_kj":145644,"rail_mrt_kajang":197971,"rail_mrt_pjy":33511,"rail_monorail":66380,"bus_rkl":16197},{"date":"2026-05-03","rail_lrt_ampang":58143,"rail_lrt_kj":120338,"rail_mrt_kajang":139501,"rail_mrt_pjy":31307,"rail_monorail":44976,"bus_rkl":12824},{"date":"2026-05-04","rail_lrt_ampang":84508,"rail_lrt_kj":226939,"rail_mrt_kajang":219912,"rail_mrt_pjy":54872,"rail_monorail":51624,"bus_rkl":26845},{"date":"2026-05-05","rail_lrt_ampang":85989,"rail_lrt_kj":239211,"rail_mrt_kajang":230305,"rail_mrt_pjy":55060,"rail_monorail":51000,"bus_rkl":28027},{"date":"2026-05-06","rail_lrt_ampang":84801,"rail_lrt_kj":246140,"rail_mrt_kajang":235268,"rail_mrt_pjy":57028,"rail_monorail":51811,"bus_rkl":28938},{"date":"2026-05-07","rail_lrt_ampang":84854,"rail_lrt_kj":239934,"rail_mrt_kajang":233525,"rail_mrt_pjy":56276,"rail_monorail":52775,"bus_rkl":28323},{"date":"2026-05-08","rail_lrt_ampang":87336,"rail_lrt_kj":236116,"rail_mrt_kajang":234136,"rail_mrt_pjy":55722,"rail_monorail":57197,"bus_rkl":27032},{"date":"2026-05-09","rail_lrt_ampang":63835,"rail_lrt_kj":141468,"rail_mrt_kajang":171443,"rail_mrt_pjy":35147,"rail_monorail":48545,"bus_rkl":16501},{"date":"2026-05-10","rail_lrt_ampang":60914,"rail_lrt_kj":125273,"rail_mrt_kajang":145988,"rail_mrt_pjy":35264,"rail_monorail":44412,"bus_rkl":13599},{"date":"2026-05-11","rail_lrt_ampang":86193,"rail_lrt_kj":233404,"rail_mrt_kajang":225799,"rail_mrt_pjy":55377,"rail_monorail":51003,"bus_rkl":27952},{"date":"2026-05-12","rail_lrt_ampang":84923,"rail_lrt_kj":245137,"rail_mrt_kajang":234742,"rail_mrt_pjy":55132,"rail_monorail":52576,"bus_rkl":28517},{"date":"2026-05-13","rail_lrt_ampang":83941,"rail_lrt_kj":242137,"rail_mrt_kajang":235634,"rail_mrt_pjy":55987,"rail_monorail":52609,"bus_rkl":29328},{"date":"2026-05-14","rail_lrt_ampang":84174,"rail_lrt_kj":240008,"rail_mrt_kajang":234065,"rail_mrt_pjy":54750,"rail_monorail":52174,"bus_rkl":28468},{"date":"2026-05-15","rail_lrt_ampang":85760,"rail_lrt_kj":233887,"rail_mrt_kajang":235714,"rail_mrt_pjy":54987,"rail_monorail":55895,"bus_rkl":26832},{"date":"2026-05-16","rail_lrt_ampang":62665,"rail_lrt_kj":140835,"rail_mrt_kajang":174390,"rail_mrt_pjy":33652,"rail_monorail":52148,"bus_rkl":15914},{"date":"2026-05-17","rail_lrt_ampang":59246,"rail_lrt_kj":122096,"rail_mrt_kajang":142526,"rail_mrt_pjy":30547,"rail_monorail":42499,"bus_rkl":13076},{"date":"2026-05-18","rail_lrt_ampang":84194,"rail_lrt_kj":220200,"rail_mrt_kajang":224237,"rail_mrt_pjy":55217,"rail_monorail":49600,"bus_rkl":26795},{"date":"2026-05-19","rail_lrt_ampang":85127,"rail_lrt_kj":236171,"rail_mrt_kajang":232402,"rail_mrt_pjy":55971,"rail_monorail":50234,"bus_rkl":28528},{"date":"2026-05-20","rail_lrt_ampang":86310,"rail_lrt_kj":241505,"rail_mrt_kajang":240656,"rail_mrt_pjy":57570,"rail_monorail":51811,"bus_rkl":29756},{"date":"2026-05-21","rail_lrt_ampang":85304,"rail_lrt_kj":236302,"rail_mrt_kajang":235403,"rail_mrt_pjy":57728,"rail_monorail":50972,"bus_rkl":28829},{"date":"2026-05-22","rail_lrt_ampang":88027,"rail_lrt_kj":237557,"rail_mrt_kajang":240483,"rail_mrt_pjy":59556,"rail_monorail":55183,"bus_rkl":27410},{"date":"2026-05-23","rail_lrt_ampang":62547,"rail_lrt_kj":140306,"rail_mrt_kajang":166955,"rail_mrt_pjy":55037,"rail_monorail":46103,"bus_rkl":15288}]